MANIFEST.in
README.rst
apihero
setup.py
apihero/__init__.py
apihero.egg-info/PKG-INFO
apihero.egg-info/SOURCES.txt
apihero.egg-info/dependency_links.txt
apihero.egg-info/not-zip-safe
apihero.egg-info/requires.txt
apihero.egg-info/top_level.txt
apihero/templates/bootstrap-material/base-level-2.html
apihero/templates/bootstrap-material/base.html
apihero/templates/bootstrap-material/docs_list.html
apihero/templates/bootstrap-material/docs_single.html
apihero/templates/bootstrap-material/index.html
apihero/templates/bootstrap-material/assets/css/bootstrap.min.css
apihero/templates/bootstrap-material/assets/css/style.css
apihero/templates/bootstrap-material/assets/img/blueprint-pattern.jpg
apihero/templates/bootstrap-material/assets/js/bootstrap.min.js
apihero/templates/bootstrap-material/assets/js/jquery.min.js
apihero/templates/bootstrap-material/assets/js/script.js
bin/apihero