Metadata-Version: 1.1
Name: apihero
Version: 0.1.2
Summary: RESTful JSON API documentation generator tool with live unit test.
Home-page: http://github.com/meyt/apihero
Author: Mahdi Ghane.g
Author-email: UNKNOWN
License: GPLv3
Keywords: apihero api_documentation api document_generator
Platform: UNKNOWN
Classifier: Development Status :: 3 - Alpha
Classifier: Environment :: Console
Classifier: Intended Audience :: Developers
Classifier: License :: OSI Approved :: GNU General Public License (GPL)
Classifier: Operating System :: POSIX :: Linux
Classifier: Operating System :: Unix
Classifier: Programming Language :: Python :: 3 :: Only
Classifier: Topic :: Software Development :: Documentation
Classifier: Topic :: Documentation
Classifier: Topic :: Software Development :: Build Tools
